iremdict/__init__.py
iremdict/cleaner.py
iremdict/data/sozluk.txt
iremdict-0.1.9.dist-info/METADATA
iremdict-0.1.9.dist-info/WHEEL
iremdict-0.1.9.dist-info/top_level.txt
iremdict-0.1.9.dist-info/RECORD
