Metadata-Version: 2.4
Name: iremdict
Version: 0.1.9
Summary: Türkçe metin temizleme için kelime sözlüğü paketi
Home-page: https://github.com/kullaniciadi/iremdict
Author: İrem Yılmaz
Author-email: iremyilmaz@example.com
License: MIT
Classifier: Programming Language :: Python :: 3
Classifier: Operating System :: OS Independent
Classifier: Natural Language :: Turkish
Classifier: License :: OSI Approved :: MIT License
Requires-Python: >=3.7
Requires-Dist: os
Dynamic: author
Dynamic: author-email
Dynamic: classifier
Dynamic: description
Dynamic: description-content-type
Dynamic: home-page
Dynamic: license
Dynamic: requires-dist
Dynamic: requires-python
Dynamic: summary
